Workbook

Sheet Start Here
A1: Income & Expense Tracker — how to use One entry tab, everything else computes. Every dollar in or out gets one row on Entries, dated. Categories map to the common US Schedule C-style deduction buckets so tax time is a filter, not an archaeology dig. IMPORTANT: Categories are common deduction categories for a US sole proprietor — confirm everything with your tax pro. This sheet organizes your numbers; it is not tax advice. 1. Entries: fill the yellow columns. Amount is always positive — the Type column carries the sign logic. For Vehicle / Mileage rows, log MILES DRIVEN in the Miles column (leave Amount 0). 2. Categories: set up once. Update the IRS standard mileage rate each January. 3. Monthly P&L and Year Dashboard build themselves. Habit that makes this work: enter every transaction within 48 hours. Ten minutes on Sunday beats four miserable days in April.

Sheet Entries
A1: Date | B1: Type | C1: Category | D1: Description | E1: Amount ($) | F1: Payment Method | G1: Month | H1: Miles (if vehicle row) | J1: Categories are common deduction categories for a US sole proprietor — confirm everything with your tax pro. This sheet organizes your numbers; it is not tax advice.
A2: 46205 | B2: Income | C2: Cleaning revenue | D2: Harmon — biweekly clean | E2: 150 | F2: Zelle | G2: =IF(A2="","",EOMONTH(A2,0))
A3: 46205 | B3: Expense | C3: Supplies | D3: Costco — microfiber, degreaser, bags | E3: 64.38 | F3: Card | G3: =IF(A3="","",EOMONTH(A3,0))
A4: 46206 | B4: Expense | C4: Vehicle / Mileage | D4: Route miles Mon–Fri | E4: 0 | F4: — | G4: =IF(A4="","",EOMONTH(A4,0)) | H4: 118
A5: 46208 | B5: Expense | C5: Advertising | D5: Google Local Services ads | E5: 75 | F5: Card | G5: =IF(A5="","",EOMONTH(A5,0))
G6: =IF(A6="","",EOMONTH(A6,0))
G7: =IF(A7="","",EOMONTH(A7,0))
G8: =IF(A8="","",EOMONTH(A8,0))
G9: =IF(A9="","",EOMONTH(A9,0))
G10: =IF(A10="","",EOMONTH(A10,0))
G11: =IF(A11="","",EOMONTH(A11,0))
G12: =IF(A12="","",EOMONTH(A12,0))
G13: =IF(A13="","",EOMONTH(A13,0))
G14: =IF(A14="","",EOMONTH(A14,0))
G15: =IF(A15="","",EOMONTH(A15,0))
G16: =IF(A16="","",EOMONTH(A16,0))
G17: =IF(A17="","",EOMONTH(A17,0))
... G1000: =IF(A1000="","",EOMONTH(A1000,0))

Sheet Categories
A1: Category | B1: Type | C1: What goes here
A2: Cleaning revenue | B2: Income | C2: All service income | E2: IRS standard mileage rate ($/mile) | F2: 0.7 | G2: Update yearly — check the current IRS standard mileage rate each January and type it here. Recent years have been around $0.65–0.70/mile.
A3: Product sales | B3: Income | C3: If you sell anything (rare, fine to ignore)
A4: Other income | B4: Income | C4: Referral fees, rebates
A5: Supplies | B5: Expense | C5: Chemicals, cloths, vacuum bags, mops — consumables
A6: Equipment | B6: Expense | C6: Vacuums, machines; big purchases may be depreciated — ask your tax pro
A7: Vehicle / Mileage | B7: Expense | C7: Log MILES in col H; dollar value computed at year level
A8: Insurance | B8: Expense | C8: General liability, bonding
A9: Advertising | B9: Expense | C9: Google/Facebook ads, flyers, car magnets, website
A10: Phone & Internet | B10: Expense | C10: Business-use share
A11: Software & Subscriptions | B11: Expense | C11: Scheduling app, accounting, this kit's future competitors
A12: Licenses & Permits | B12: Expense | C12: Business license, city registrations
A13: Legal & Professional | B13: Expense | C13: Tax prep, LLC filing help
A14: Contract Labor | B14: Expense | C14: 1099 help — talk to your tax pro before hiring
... A17: Other expense | B17: Expense | C17: Anything that truly fits nowhere — keep this small

Sheet Monthly P&L
A1: Category | B1: =DATE(2026,1,31) | C1: =EOMONTH(B1,1) | D1: =EOMONTH(C1,1) | E1: =EOMONTH(D1,1) | F1: =EOMONTH(E1,1) | G1: =EOMONTH(F1,1) | H1: =EOMONTH(G1,1) | I1: =EOMONTH(H1,1) | J1: =EOMONTH(I1,1) | ... M1: =EOMONTH(L1,1)
A2: INCOME
A3: =Categories!A2 | B3: =SUMIFS(Entries!$E$2:$E$1000,Entries!$C$2:$C$1000,$A3,Entries!$G$2:$G$1000,B$1) | C3: =SUMIFS(Entries!$E$2:$E$1000,Entries!$C$2:$C$1000,$A3,Entries!$G$2:$G$1000,C$1) | D3: =SUMIFS(Entries!$E$2:$E$1000,Entries!$C$2:$C$1000,$A3,Entries!$G$2:$G$1000,D$1) | E3: =SUMIFS(Entries!$E$2:$E$1000,Entries!$C$2:$C$1000,$A3,Entries!$G$2:$G$1000,E$1) | F3: =SUMIFS(Entries!$E$2:$E$1000,Entries!$C$2:$C$1000,$A3,Entries!$G$2:$G$1000,F$1) | G3: =SUMIFS(Entries!$E$2:$E$1000,Entries!$C$2:$C$1000,$A3,Entries!$G$2:$G$1000,G$1) | H3: =SUMIFS(Entries!$E$2:$E$1000,Entries!$C$2:$C$1000,$A3,Entries!$G$2:$G$1000,H$1) | I3: =SUMIFS(Entries!$E$2:$E$1000,Entries!$C$2:$C$1000,$A3,Entries!$G$2:$G$1000,I$1) | ... M3: =SUMIFS(Entries!$E$2:$E$1000,Entries!$C$2:$C$1000,$A3,Entries!$G$2:$G$1000,M$1)
A4: =Categories!A3 | B4: =SUMIFS(Entries!$E$2:$E$1000,Entries!$C$2:$C$1000,$A4,Entries!$G$2:$G$1000,B$1) | C4: =SUMIFS(Entries!$E$2:$E$1000,Entries!$C$2:$C$1000,$A4,Entries!$G$2:$G$1000,C$1) | D4: =SUMIFS(Entries!$E$2:$E$1000,Entries!$C$2:$C$1000,$A4,Entries!$G$2:$G$1000,D$1) | E4: =SUMIFS(Entries!$E$2:$E$1000,Entries!$C$2:$C$1000,$A4,Entries!$G$2:$G$1000,E$1) | F4: =SUMIFS(Entries!$E$2:$E$1000,Entries!$C$2:$C$1000,$A4,Entries!$G$2:$G$1000,F$1) | G4: =SUMIFS(Entries!$E$2:$E$1000,Entries!$C$2:$C$1000,$A4,Entries!$G$2:$G$1000,G$1) | H4: =SUMIFS(Entries!$E$2:$E$1000,Entries!$C$2:$C$1000,$A4,Entries!$G$2:$G$1000,H$1) | I4: =SUMIFS(Entries!$E$2:$E$1000,Entries!$C$2:$C$1000,$A4,Entries!$G$2:$G$1000,I$1) | ... M4: =SUMIFS(Entries!$E$2:$E$1000,Entries!$C$2:$C$1000,$A4,Entries!$G$2:$G$1000,M$1)
A5: =Categories!A4 | B5: =SUMIFS(Entries!$E$2:$E$1000,Entries!$C$2:$C$1000,$A5,Entries!$G$2:$G$1000,B$1) | C5: =SUMIFS(Entries!$E$2:$E$1000,Entries!$C$2:$C$1000,$A5,Entries!$G$2:$G$1000,C$1) | D5: =SUMIFS(Entries!$E$2:$E$1000,Entries!$C$2:$C$1000,$A5,Entries!$G$2:$G$1000,D$1) | E5: =SUMIFS(Entries!$E$2:$E$1000,Entries!$C$2:$C$1000,$A5,Entries!$G$2:$G$1000,E$1) | F5: =SUMIFS(Entries!$E$2:$E$1000,Entries!$C$2:$C$1000,$A5,Entries!$G$2:$G$1000,F$1) | G5: =SUMIFS(Entries!$E$2:$E$1000,Entries!$C$2:$C$1000,$A5,Entries!$G$2:$G$1000,G$1) | H5: =SUMIFS(Entries!$E$2:$E$1000,Entries!$C$2:$C$1000,$A5,Entries!$G$2:$G$1000,H$1) | I5: =SUMIFS(Entries!$E$2:$E$1000,Entries!$C$2:$C$1000,$A5,Entries!$G$2:$G$1000,I$1) | ... M5: =SUMIFS(Entries!$E$2:$E$1000,Entries!$C$2:$C$1000,$A5,Entries!$G$2:$G$1000,M$1)
A6: Total Income | B6: =SUM(B3:B5) | C6: =SUM(C3:C5) | D6: =SUM(D3:D5) | E6: =SUM(E3:E5) | F6: =SUM(F3:F5) | G6: =SUM(G3:G5) | H6: =SUM(H3:H5) | I6: =SUM(I3:I5) | ... M6: =SUM(M3:M5)
A8: EXPENSES
A9: =Categories!A5 | B9: =SUMIFS(Entries!$E$2:$E$1000,Entries!$C$2:$C$1000,$A9,Entries!$G$2:$G$1000,B$1) | C9: =SUMIFS(Entries!$E$2:$E$1000,Entries!$C$2:$C$1000,$A9,Entries!$G$2:$G$1000,C$1) | D9: =SUMIFS(Entries!$E$2:$E$1000,Entries!$C$2:$C$1000,$A9,Entries!$G$2:$G$1000,D$1) | E9: =SUMIFS(Entries!$E$2:$E$1000,Entries!$C$2:$C$1000,$A9,Entries!$G$2:$G$1000,E$1) | F9: =SUMIFS(Entries!$E$2:$E$1000,Entries!$C$2:$C$1000,$A9,Entries!$G$2:$G$1000,F$1) | G9: =SUMIFS(Entries!$E$2:$E$1000,Entries!$C$2:$C$1000,$A9,Entries!$G$2:$G$1000,G$1) | H9: =SUMIFS(Entries!$E$2:$E$1000,Entries!$C$2:$C$1000,$A9,Entries!$G$2:$G$1000,H$1) | I9: =SUMIFS(Entries!$E$2:$E$1000,Entries!$C$2:$C$1000,$A9,Entries!$G$2:$G$1000,I$1) | ... M9: =SUMIFS(Entries!$E$2:$E$1000,Entries!$C$2:$C$1000,$A9,Entries!$G$2:$G$1000,M$1)
A10: =Categories!A6 | B10: =SUMIFS(Entries!$E$2:$E$1000,Entries!$C$2:$C$1000,$A10,Entries!$G$2:$G$1000,B$1) | C10: =SUMIFS(Entries!$E$2:$E$1000,Entries!$C$2:$C$1000,$A10,Entries!$G$2:$G$1000,C$1) | D10: =SUMIFS(Entries!$E$2:$E$1000,Entries!$C$2:$C$1000,$A10,Entries!$G$2:$G$1000,D$1) | E10: =SUMIFS(Entries!$E$2:$E$1000,Entries!$C$2:$C$1000,$A10,Entries!$G$2:$G$1000,E$1) | F10: =SUMIFS(Entries!$E$2:$E$1000,Entries!$C$2:$C$1000,$A10,Entries!$G$2:$G$1000,F$1) | G10: =SUMIFS(Entries!$E$2:$E$1000,Entries!$C$2:$C$1000,$A10,Entries!$G$2:$G$1000,G$1) | H10: =SUMIFS(Entries!$E$2:$E$1000,Entries!$C$2:$C$1000,$A10,Entries!$G$2:$G$1000,H$1) | I10: =SUMIFS(Entries!$E$2:$E$1000,Entries!$C$2:$C$1000,$A10,Entries!$G$2:$G$1000,I$1) | ... M10: =SUMIFS(Entries!$E$2:$E$1000,Entries!$C$2:$C$1000,$A10,Entries!$G$2:$G$1000,M$1)
A11: =Categories!A7 | B11: =SUMIFS(Entries!$E$2:$E$1000,Entries!$C$2:$C$1000,$A11,Entries!$G$2:$G$1000,B$1) | C11: =SUMIFS(Entries!$E$2:$E$1000,Entries!$C$2:$C$1000,$A11,Entries!$G$2:$G$1000,C$1) | D11: =SUMIFS(Entries!$E$2:$E$1000,Entries!$C$2:$C$1000,$A11,Entries!$G$2:$G$1000,D$1) | E11: =SUMIFS(Entries!$E$2:$E$1000,Entries!$C$2:$C$1000,$A11,Entries!$G$2:$G$1000,E$1) | F11: =SUMIFS(Entries!$E$2:$E$1000,Entries!$C$2:$C$1000,$A11,Entries!$G$2:$G$1000,F$1) | G11: =SUMIFS(Entries!$E$2:$E$1000,Entries!$C$2:$C$1000,$A11,Entries!$G$2:$G$1000,G$1) | H11: =SUMIFS(Entries!$E$2:$E$1000,Entries!$C$2:$C$1000,$A11,Entries!$G$2:$G$1000,H$1) | I11: =SUMIFS(Entries!$E$2:$E$1000,Entries!$C$2:$C$1000,$A11,Entries!$G$2:$G$1000,I$1) | ... M11: =SUMIFS(Entries!$E$2:$E$1000,Entries!$C$2:$C$1000,$A11,Entries!$G$2:$G$1000,M$1)
A12: =Categories!A8 | B12: =SUMIFS(Entries!$E$2:$E$1000,Entries!$C$2:$C$1000,$A12,Entries!$G$2:$G$1000,B$1) | C12: =SUMIFS(Entries!$E$2:$E$1000,Entries!$C$2:$C$1000,$A12,Entries!$G$2:$G$1000,C$1) | D12: =SUMIFS(Entries!$E$2:$E$1000,Entries!$C$2:$C$1000,$A12,Entries!$G$2:$G$1000,D$1) | E12: =SUMIFS(Entries!$E$2:$E$1000,Entries!$C$2:$C$1000,$A12,Entries!$G$2:$G$1000,E$1) | F12: =SUMIFS(Entries!$E$2:$E$1000,Entries!$C$2:$C$1000,$A12,Entries!$G$2:$G$1000,F$1) | G12: =SUMIFS(Entries!$E$2:$E$1000,Entries!$C$2:$C$1000,$A12,Entries!$G$2:$G$1000,G$1) | H12: =SUMIFS(Entries!$E$2:$E$1000,Entries!$C$2:$C$1000,$A12,Entries!$G$2:$G$1000,H$1) | I12: =SUMIFS(Entries!$E$2:$E$1000,Entries!$C$2:$C$1000,$A12,Entries!$G$2:$G$1000,I$1) | ... M12: =SUMIFS(Entries!$E$2:$E$1000,Entries!$C$2:$C$1000,$A12,Entries!$G$2:$G$1000,M$1)
A13: =Categories!A9 | B13: =SUMIFS(Entries!$E$2:$E$1000,Entries!$C$2:$C$1000,$A13,Entries!$G$2:$G$1000,B$1) | C13: =SUMIFS(Entries!$E$2:$E$1000,Entries!$C$2:$C$1000,$A13,Entries!$G$2:$G$1000,C$1) | D13: =SUMIFS(Entries!$E$2:$E$1000,Entries!$C$2:$C$1000,$A13,Entries!$G$2:$G$1000,D$1) | E13: =SUMIFS(Entries!$E$2:$E$1000,Entries!$C$2:$C$1000,$A13,Entries!$G$2:$G$1000,E$1) | F13: =SUMIFS(Entries!$E$2:$E$1000,Entries!$C$2:$C$1000,$A13,Entries!$G$2:$G$1000,F$1) | G13: =SUMIFS(Entries!$E$2:$E$1000,Entries!$C$2:$C$1000,$A13,Entries!$G$2:$G$1000,G$1) | H13: =SUMIFS(Entries!$E$2:$E$1000,Entries!$C$2:$C$1000,$A13,Entries!$G$2:$G$1000,H$1) | I13: =SUMIFS(Entries!$E$2:$E$1000,Entries!$C$2:$C$1000,$A13,Entries!$G$2:$G$1000,I$1) | ... M13: =SUMIFS(Entries!$E$2:$E$1000,Entries!$C$2:$C$1000,$A13,Entries!$G$2:$G$1000,M$1)
A14: =Categories!A10 | B14: =SUMIFS(Entries!$E$2:$E$1000,Entries!$C$2:$C$1000,$A14,Entries!$G$2:$G$1000,B$1) | C14: =SUMIFS(Entries!$E$2:$E$1000,Entries!$C$2:$C$1000,$A14,Entries!$G$2:$G$1000,C$1) | D14: =SUMIFS(Entries!$E$2:$E$1000,Entries!$C$2:$C$1000,$A14,Entries!$G$2:$G$1000,D$1) | E14: =SUMIFS(Entries!$E$2:$E$1000,Entries!$C$2:$C$1000,$A14,Entries!$G$2:$G$1000,E$1) | F14: =SUMIFS(Entries!$E$2:$E$1000,Entries!$C$2:$C$1000,$A14,Entries!$G$2:$G$1000,F$1) | G14: =SUMIFS(Entries!$E$2:$E$1000,Entries!$C$2:$C$1000,$A14,Entries!$G$2:$G$1000,G$1) | H14: =SUMIFS(Entries!$E$2:$E$1000,Entries!$C$2:$C$1000,$A14,Entries!$G$2:$G$1000,H$1) | I14: =SUMIFS(Entries!$E$2:$E$1000,Entries!$C$2:$C$1000,$A14,Entries!$G$2:$G$1000,I$1) | ... M14: =SUMIFS(Entries!$E$2:$E$1000,Entries!$C$2:$C$1000,$A14,Entries!$G$2:$G$1000,M$1)
A15: =Categories!A11 | B15: =SUMIFS(Entries!$E$2:$E$1000,Entries!$C$2:$C$1000,$A15,Entries!$G$2:$G$1000,B$1) | C15: =SUMIFS(Entries!$E$2:$E$1000,Entries!$C$2:$C$1000,$A15,Entries!$G$2:$G$1000,C$1) | D15: =SUMIFS(Entries!$E$2:$E$1000,Entries!$C$2:$C$1000,$A15,Entries!$G$2:$G$1000,D$1) | E15: =SUMIFS(Entries!$E$2:$E$1000,Entries!$C$2:$C$1000,$A15,Entries!$G$2:$G$1000,E$1) | F15: =SUMIFS(Entries!$E$2:$E$1000,Entries!$C$2:$C$1000,$A15,Entries!$G$2:$G$1000,F$1) | G15: =SUMIFS(Entries!$E$2:$E$1000,Entries!$C$2:$C$1000,$A15,Entries!$G$2:$G$1000,G$1) | H15: =SUMIFS(Entries!$E$2:$E$1000,Entries!$C$2:$C$1000,$A15,Entries!$G$2:$G$1000,H$1) | I15: =SUMIFS(Entries!$E$2:$E$1000,Entries!$C$2:$C$1000,$A15,Entries!$G$2:$G$1000,I$1) | ... M15: =SUMIFS(Entries!$E$2:$E$1000,Entries!$C$2:$C$1000,$A15,Entries!$G$2:$G$1000,M$1)
A16: =Categories!A12 | B16: =SUMIFS(Entries!$E$2:$E$1000,Entries!$C$2:$C$1000,$A16,Entries!$G$2:$G$1000,B$1) | C16: =SUMIFS(Entries!$E$2:$E$1000,Entries!$C$2:$C$1000,$A16,Entries!$G$2:$G$1000,C$1) | D16: =SUMIFS(Entries!$E$2:$E$1000,Entries!$C$2:$C$1000,$A16,Entries!$G$2:$G$1000,D$1) | E16: =SUMIFS(Entries!$E$2:$E$1000,Entries!$C$2:$C$1000,$A16,Entries!$G$2:$G$1000,E$1) | F16: =SUMIFS(Entries!$E$2:$E$1000,Entries!$C$2:$C$1000,$A16,Entries!$G$2:$G$1000,F$1) | G16: =SUMIFS(Entries!$E$2:$E$1000,Entries!$C$2:$C$1000,$A16,Entries!$G$2:$G$1000,G$1) | H16: =SUMIFS(Entries!$E$2:$E$1000,Entries!$C$2:$C$1000,$A16,Entries!$G$2:$G$1000,H$1) | I16: =SUMIFS(Entries!$E$2:$E$1000,Entries!$C$2:$C$1000,$A16,Entries!$G$2:$G$1000,I$1) | ... M16: =SUMIFS(Entries!$E$2:$E$1000,Entries!$C$2:$C$1000,$A16,Entries!$G$2:$G$1000,M$1)
A17: =Categories!A13 | B17: =SUMIFS(Entries!$E$2:$E$1000,Entries!$C$2:$C$1000,$A17,Entries!$G$2:$G$1000,B$1) | C17: =SUMIFS(Entries!$E$2:$E$1000,Entries!$C$2:$C$1000,$A17,Entries!$G$2:$G$1000,C$1) | D17: =SUMIFS(Entries!$E$2:$E$1000,Entries!$C$2:$C$1000,$A17,Entries!$G$2:$G$1000,D$1) | E17: =SUMIFS(Entries!$E$2:$E$1000,Entries!$C$2:$C$1000,$A17,Entries!$G$2:$G$1000,E$1) | F17: =SUMIFS(Entries!$E$2:$E$1000,Entries!$C$2:$C$1000,$A17,Entries!$G$2:$G$1000,F$1) | G17: =SUMIFS(Entries!$E$2:$E$1000,Entries!$C$2:$C$1000,$A17,Entries!$G$2:$G$1000,G$1) | H17: =SUMIFS(Entries!$E$2:$E$1000,Entries!$C$2:$C$1000,$A17,Entries!$G$2:$G$1000,H$1) | I17: =SUMIFS(Entries!$E$2:$E$1000,Entries!$C$2:$C$1000,$A17,Entries!$G$2:$G$1000,I$1) | ... M17: =SUMIFS(Entries!$E$2:$E$1000,Entries!$C$2:$C$1000,$A17,Entries!$G$2:$G$1000,M$1)
A18: =Categories!A14 | B18: =SUMIFS(Entries!$E$2:$E$1000,Entries!$C$2:$C$1000,$A18,Entries!$G$2:$G$1000,B$1) | C18: =SUMIFS(Entries!$E$2:$E$1000,Entries!$C$2:$C$1000,$A18,Entries!$G$2:$G$1000,C$1) | D18: =SUMIFS(Entries!$E$2:$E$1000,Entries!$C$2:$C$1000,$A18,Entries!$G$2:$G$1000,D$1) | E18: =SUMIFS(Entries!$E$2:$E$1000,Entries!$C$2:$C$1000,$A18,Entries!$G$2:$G$1000,E$1) | F18: =SUMIFS(Entries!$E$2:$E$1000,Entries!$C$2:$C$1000,$A18,Entries!$G$2:$G$1000,F$1) | G18: =SUMIFS(Entries!$E$2:$E$1000,Entries!$C$2:$C$1000,$A18,Entries!$G$2:$G$1000,G$1) | H18: =SUMIFS(Entries!$E$2:$E$1000,Entries!$C$2:$C$1000,$A18,Entries!$G$2:$G$1000,H$1) | I18: =SUMIFS(Entries!$E$2:$E$1000,Entries!$C$2:$C$1000,$A18,Entries!$G$2:$G$1000,I$1) | ... M18: =SUMIFS(Entries!$E$2:$E$1000,Entries!$C$2:$C$1000,$A18,Entries!$G$2:$G$1000,M$1)
A19: =Categories!A15 | B19: =SUMIFS(Entries!$E$2:$E$1000,Entries!$C$2:$C$1000,$A19,Entries!$G$2:$G$1000,B$1) | C19: =SUMIFS(Entries!$E$2:$E$1000,Entries!$C$2:$C$1000,$A19,Entries!$G$2:$G$1000,C$1) | D19: =SUMIFS(Entries!$E$2:$E$1000,Entries!$C$2:$C$1000,$A19,Entries!$G$2:$G$1000,D$1) | E19: =SUMIFS(Entries!$E$2:$E$1000,Entries!$C$2:$C$1000,$A19,Entries!$G$2:$G$1000,E$1) | F19: =SUMIFS(Entries!$E$2:$E$1000,Entries!$C$2:$C$1000,$A19,Entries!$G$2:$G$1000,F$1) | G19: =SUMIFS(Entries!$E$2:$E$1000,Entries!$C$2:$C$1000,$A19,Entries!$G$2:$G$1000,G$1) | H19: =SUMIFS(Entries!$E$2:$E$1000,Entries!$C$2:$C$1000,$A19,Entries!$G$2:$G$1000,H$1) | I19: =SUMIFS(Entries!$E$2:$E$1000,Entries!$C$2:$C$1000,$A19,Entries!$G$2:$G$1000,I$1) | ... M19: =SUMIFS(Entries!$E$2:$E$1000,Entries!$C$2:$C$1000,$A19,Entries!$G$2:$G$1000,M$1)
A20: =Categories!A16 | B20: =SUMIFS(Entries!$E$2:$E$1000,Entries!$C$2:$C$1000,$A20,Entries!$G$2:$G$1000,B$1) | C20: =SUMIFS(Entries!$E$2:$E$1000,Entries!$C$2:$C$1000,$A20,Entries!$G$2:$G$1000,C$1) | D20: =SUMIFS(Entries!$E$2:$E$1000,Entries!$C$2:$C$1000,$A20,Entries!$G$2:$G$1000,D$1) | E20: =SUMIFS(Entries!$E$2:$E$1000,Entries!$C$2:$C$1000,$A20,Entries!$G$2:$G$1000,E$1) | F20: =SUMIFS(Entries!$E$2:$E$1000,Entries!$C$2:$C$1000,$A20,Entries!$G$2:$G$1000,F$1) | G20: =SUMIFS(Entries!$E$2:$E$1000,Entries!$C$2:$C$1000,$A20,Entries!$G$2:$G$1000,G$1) | H20: =SUMIFS(Entries!$E$2:$E$1000,Entries!$C$2:$C$1000,$A20,Entries!$G$2:$G$1000,H$1) | I20: =SUMIFS(Entries!$E$2:$E$1000,Entries!$C$2:$C$1000,$A20,Entries!$G$2:$G$1000,I$1) | ... M20: =SUMIFS(Entries!$E$2:$E$1000,Entries!$C$2:$C$1000,$A20,Entries!$G$2:$G$1000,M$1)
A21: =Categories!A17 | B21: =SUMIFS(Entries!$E$2:$E$1000,Entries!$C$2:$C$1000,$A21,Entries!$G$2:$G$1000,B$1) | C21: =SUMIFS(Entries!$E$2:$E$1000,Entries!$C$2:$C$1000,$A21,Entries!$G$2:$G$1000,C$1) | D21: =SUMIFS(Entries!$E$2:$E$1000,Entries!$C$2:$C$1000,$A21,Entries!$G$2:$G$1000,D$1) | E21: =SUMIFS(Entries!$E$2:$E$1000,Entries!$C$2:$C$1000,$A21,Entries!$G$2:$G$1000,E$1) | F21: =SUMIFS(Entries!$E$2:$E$1000,Entries!$C$2:$C$1000,$A21,Entries!$G$2:$G$1000,F$1) | G21: =SUMIFS(Entries!$E$2:$E$1000,Entries!$C$2:$C$1000,$A21,Entries!$G$2:$G$1000,G$1) | H21: =SUMIFS(Entries!$E$2:$E$1000,Entries!$C$2:$C$1000,$A21,Entries!$G$2:$G$1000,H$1) | I21: =SUMIFS(Entries!$E$2:$E$1000,Entries!$C$2:$C$1000,$A21,Entries!$G$2:$G$1000,I$1) | ... M21: =SUMIFS(Entries!$E$2:$E$1000,Entries!$C$2:$C$1000,$A21,Entries!$G$2:$G$1000,M$1)
A22: Total Expenses | B22: =SUM(B9:B21) | C22: =SUM(C9:C21) | D22: =SUM(D9:D21) | E22: =SUM(E9:E21) | F22: =SUM(F9:F21) | G22: =SUM(G9:G21) | H22: =SUM(H9:H21) | I22: =SUM(I9:I21) | ... M22: =SUM(M9:M21)
A23: Net Profit | B23: =B6-B22 | C23: =C6-C22 | D23: =D6-D22 | E23: =E6-E22 | F23: =F6-F22 | G23: =G6-G22 | H23: =H6-H22 | I23: =I6-I22 | ... M23: =M6-M22
A24: Miles Driven | B24: =SUMIFS(Entries!$H$2:$H$1000,Entries!$G$2:$G$1000,B$1) | C24: =SUMIFS(Entries!$H$2:$H$1000,Entries!$G$2:$G$1000,C$1) | D24: =SUMIFS(Entries!$H$2:$H$1000,Entries!$G$2:$G$1000,D$1) | E24: =SUMIFS(Entries!$H$2:$H$1000,Entries!$G$2:$G$1000,E$1) | F24: =SUMIFS(Entries!$H$2:$H$1000,Entries!$G$2:$G$1000,F$1) | G24: =SUMIFS(Entries!$H$2:$H$1000,Entries!$G$2:$G$1000,G$1) | H24: =SUMIFS(Entries!$H$2:$H$1000,Entries!$G$2:$G$1000,H$1) | I24: =SUMIFS(Entries!$H$2:$H$1000,Entries!$G$2:$G$1000,I$1) | ... M24: =SUMIFS(Entries!$H$2:$H$1000,Entries!$G$2:$G$1000,M$1)
A25: Mileage Deduction (est.) | B25: =ROUND(SUMIFS(Entries!$H$2:$H$1000,Entries!$G$2:$G$1000,B$1)*Categories!$F$2,2) | C25: =ROUND(SUMIFS(Entries!$H$2:$H$1000,Entries!$G$2:$G$1000,C$1)*Categories!$F$2,2) | D25: =ROUND(SUMIFS(Entries!$H$2:$H$1000,Entries!$G$2:$G$1000,D$1)*Categories!$F$2,2) | E25: =ROUND(SUMIFS(Entries!$H$2:$H$1000,Entries!$G$2:$G$1000,E$1)*Categories!$F$2,2) | F25: =ROUND(SUMIFS(Entries!$H$2:$H$1000,Entries!$G$2:$G$1000,F$1)*Categories!$F$2,2) | G25: =ROUND(SUMIFS(Entries!$H$2:$H$1000,Entries!$G$2:$G$1000,G$1)*Categories!$F$2,2) | H25: =ROUND(SUMIFS(Entries!$H$2:$H$1000,Entries!$G$2:$G$1000,H$1)*Categories!$F$2,2) | I25: =ROUND(SUMIFS(Entries!$H$2:$H$1000,Entries!$G$2:$G$1000,I$1)*Categories!$F$2,2) | ... M25: =ROUND(SUMIFS(Entries!$H$2:$H$1000,Entries!$G$2:$G$1000,M$1)*Categories!$F$2,2)
A27: Mileage deduction shown for planning only — it is not included in Net Profit above because it's a deduction, not a cash expense. Your tax pro reconciles this at filing.

Sheet Year Dashboard
A1: YEAR DASHBOARD | D1: TOP EXPENSE CATEGORIES
A2: YTD Revenue | B2: =SUMIFS(Entries!$E$2:$E$1000,Entries!$B$2:$B$1000,"Income") | D2: Category | E2: Total ($) | F2: Rank (1 = biggest)
A3: YTD Expenses | B3: =SUMIFS(Entries!$E$2:$E$1000,Entries!$B$2:$B$1000,"Expense") | D3: =Categories!A5 | E3: =SUMIFS(Entries!$E$2:$E$1000,Entries!$C$2:$C$1000,$D3) | F3: =IF(E3=0,"",RANK(E3,$E$3:$E$15))
A4: YTD Net Profit | B4: =B2-B3 | D4: =Categories!A6 | E4: =SUMIFS(Entries!$E$2:$E$1000,Entries!$C$2:$C$1000,$D4) | F4: =IF(E4=0,"",RANK(E4,$E$3:$E$15))
A5: Profit Margin | B5: =IF(B2=0,"",B4/B2) | D5: =Categories!A7 | E5: =SUMIFS(Entries!$E$2:$E$1000,Entries!$C$2:$C$1000,$D5) | F5: =IF(E5=0,"",RANK(E5,$E$3:$E$15))
A6: YTD Miles | B6: =SUM(Entries!$H$2:$H$1000) | D6: =Categories!A8 | E6: =SUMIFS(Entries!$E$2:$E$1000,Entries!$C$2:$C$1000,$D6) | F6: =IF(E6=0,"",RANK(E6,$E$3:$E$15))
A7: Est. Mileage Deduction | B7: =ROUND(B6*Categories!$F$2,2) | D7: =Categories!A9 | E7: =SUMIFS(Entries!$E$2:$E$1000,Entries!$C$2:$C$1000,$D7) | F7: =IF(E7=0,"",RANK(E7,$E$3:$E$15))
A8: Best Month (profit) | B8: =IFERROR(TEXT(INDEX('Monthly P&L'!$B$1:$M$1,MATCH(MAX('Monthly P&L'!$B$23:$M$23),'Monthly P&L'!$B$23:$M$23,0)),"MMM"),"") | D8: =Categories!A10 | E8: =SUMIFS(Entries!$E$2:$E$1000,Entries!$C$2:$C$1000,$D8) | F8: =IF(E8=0,"",RANK(E8,$E$3:$E$15))
A9: Tax set-aside (25% of net) | B9: =ROUND(MAX(B4,0)*0.25,2) | C9: Rough set-aside so quarterly estimates don't ambush you; your tax pro sets the real number. | D9: =Categories!A11 | E9: =SUMIFS(Entries!$E$2:$E$1000,Entries!$C$2:$C$1000,$D9) | F9: =IF(E9=0,"",RANK(E9,$E$3:$E$15))
D10: =Categories!A12 | E10: =SUMIFS(Entries!$E$2:$E$1000,Entries!$C$2:$C$1000,$D10) | F10: =IF(E10=0,"",RANK(E10,$E$3:$E$15))
A11: Tip: insert a column chart over the Monthly P&L Net Profit row (row 23, months on the X axis). One glance tells you whether the business is growing or you're just busy. | D11: =Categories!A13 | E11: =SUMIFS(Entries!$E$2:$E$1000,Entries!$C$2:$C$1000,$D11) | F11: =IF(E11=0,"",RANK(E11,$E$3:$E$15))
D12: =Categories!A14 | E12: =SUMIFS(Entries!$E$2:$E$1000,Entries!$C$2:$C$1000,$D12) | F12: =IF(E12=0,"",RANK(E12,$E$3:$E$15))
D13: =Categories!A15 | E13: =SUMIFS(Entries!$E$2:$E$1000,Entries!$C$2:$C$1000,$D13) | F13: =IF(E13=0,"",RANK(E13,$E$3:$E$15))
D14: =Categories!A16 | E14: =SUMIFS(Entries!$E$2:$E$1000,Entries!$C$2:$C$1000,$D14) | F14: =IF(E14=0,"",RANK(E14,$E$3:$E$15))
D15: =Categories!A17 | E15: =SUMIFS(Entries!$E$2:$E$1000,Entries!$C$2:$C$1000,$D15) | F15: =IF(E15=0,"",RANK(E15,$E$3:$E$15))
