Workbook

Sheet Start Here
A1: Job Costing — how to use Quoting is a guess. Job costing is the truth. After a visit, put the ACTUAL numbers in and find out what that stop really paid. Do this for a full month across your whole route. The pattern that shows up will surprise you — usually a handful of long-standing clients whose price hasn't moved in three years are quietly the worst-paying stops on the route. Those are the ones to raise first. Use the price-increase letter in File 12; it's written for exactly this conversation. Convention: yellow cells = inputs (type here), green cells = outputs (never type here).

Sheet Visit Log
A1: Date | B1: Client | C1: Service | D1: Price ($) | E1: On-site Min | F1: Drive Min | G1: Fuel ($) | H1: Materials ($) | I1: Labor Cost ($) | J1: Equip Reserve ($) | K1: Total Cost ($) | L1: Profit ($) | M1: Margin | N1: True $/hr
A2: 46209 | B2: Okafor, D. | C2: Mow/Trim/Edge | D2: 55 | E2: 34 | F2: 6 | G2: 4.5 | I2: =IF(E2="","",ROUND(((E2+F2)/60)*'Cost Rates'!$B$3,2)) | J2: =IF(D2="","",'Cost Rates'!$B$4) | K2: =IF(D2="","",SUM(G2,H2,I2,J2)) | L2: =IF(D2="","",D2-K2) | M2: =IF(OR(D2="",D2=0),"",L2/D2) | N2: =IF((E2+F2)=0,"",ROUND(L2/((E2+F2)/60),2))
A3: 46209 | B3: Ruiz, M. | C3: Mow/Trim/Edge | D3: 65 | E3: 41 | F3: 2 | G3: 4.5 | I3: =IF(E3="","",ROUND(((E3+F3)/60)*'Cost Rates'!$B$3,2)) | J3: =IF(D3="","",'Cost Rates'!$B$4) | K3: =IF(D3="","",SUM(G3,H3,I3,J3)) | L3: =IF(D3="","",D3-K3) | M3: =IF(OR(D3="",D3=0),"",L3/D3) | N3: =IF((E3+F3)=0,"",ROUND(L3/((E3+F3)/60),2))
I4: =IF(E4="","",ROUND(((E4+F4)/60)*'Cost Rates'!$B$3,2)) | J4: =IF(D4="","",'Cost Rates'!$B$4) | K4: =IF(D4="","",SUM(G4,H4,I4,J4)) | L4: =IF(D4="","",D4-K4) | M4: =IF(OR(D4="",D4=0),"",L4/D4) | N4: =IF((E4+F4)=0,"",ROUND(L4/((E4+F4)/60),2))
I5: =IF(E5="","",ROUND(((E5+F5)/60)*'Cost Rates'!$B$3,2)) | J5: =IF(D5="","",'Cost Rates'!$B$4) | K5: =IF(D5="","",SUM(G5,H5,I5,J5)) | L5: =IF(D5="","",D5-K5) | M5: =IF(OR(D5="",D5=0),"",L5/D5) | N5: =IF((E5+F5)=0,"",ROUND(L5/((E5+F5)/60),2))
I6: =IF(E6="","",ROUND(((E6+F6)/60)*'Cost Rates'!$B$3,2)) | J6: =IF(D6="","",'Cost Rates'!$B$4) | K6: =IF(D6="","",SUM(G6,H6,I6,J6)) | L6: =IF(D6="","",D6-K6) | M6: =IF(OR(D6="",D6=0),"",L6/D6) | N6: =IF((E6+F6)=0,"",ROUND(L6/((E6+F6)/60),2))
I7: =IF(E7="","",ROUND(((E7+F7)/60)*'Cost Rates'!$B$3,2)) | J7: =IF(D7="","",'Cost Rates'!$B$4) | K7: =IF(D7="","",SUM(G7,H7,I7,J7)) | L7: =IF(D7="","",D7-K7) | M7: =IF(OR(D7="",D7=0),"",L7/D7) | N7: =IF((E7+F7)=0,"",ROUND(L7/((E7+F7)/60),2))
I8: =IF(E8="","",ROUND(((E8+F8)/60)*'Cost Rates'!$B$3,2)) | J8: =IF(D8="","",'Cost Rates'!$B$4) | K8: =IF(D8="","",SUM(G8,H8,I8,J8)) | L8: =IF(D8="","",D8-K8) | M8: =IF(OR(D8="",D8=0),"",L8/D8) | N8: =IF((E8+F8)=0,"",ROUND(L8/((E8+F8)/60),2))
I9: =IF(E9="","",ROUND(((E9+F9)/60)*'Cost Rates'!$B$3,2)) | J9: =IF(D9="","",'Cost Rates'!$B$4) | K9: =IF(D9="","",SUM(G9,H9,I9,J9)) | L9: =IF(D9="","",D9-K9) | M9: =IF(OR(D9="",D9=0),"",L9/D9) | N9: =IF((E9+F9)=0,"",ROUND(L9/((E9+F9)/60),2))
I10: =IF(E10="","",ROUND(((E10+F10)/60)*'Cost Rates'!$B$3,2)) | J10: =IF(D10="","",'Cost Rates'!$B$4) | K10: =IF(D10="","",SUM(G10,H10,I10,J10)) | L10: =IF(D10="","",D10-K10) | M10: =IF(OR(D10="",D10=0),"",L10/D10) | N10: =IF((E10+F10)=0,"",ROUND(L10/((E10+F10)/60),2))
I11: =IF(E11="","",ROUND(((E11+F11)/60)*'Cost Rates'!$B$3,2)) | J11: =IF(D11="","",'Cost Rates'!$B$4) | K11: =IF(D11="","",SUM(G11,H11,I11,J11)) | L11: =IF(D11="","",D11-K11) | M11: =IF(OR(D11="",D11=0),"",L11/D11) | N11: =IF((E11+F11)=0,"",ROUND(L11/((E11+F11)/60),2))
I12: =IF(E12="","",ROUND(((E12+F12)/60)*'Cost Rates'!$B$3,2)) | J12: =IF(D12="","",'Cost Rates'!$B$4) | K12: =IF(D12="","",SUM(G12,H12,I12,J12)) | L12: =IF(D12="","",D12-K12) | M12: =IF(OR(D12="",D12=0),"",L12/D12) | N12: =IF((E12+F12)=0,"",ROUND(L12/((E12+F12)/60),2))
I13: =IF(E13="","",ROUND(((E13+F13)/60)*'Cost Rates'!$B$3,2)) | J13: =IF(D13="","",'Cost Rates'!$B$4) | K13: =IF(D13="","",SUM(G13,H13,I13,J13)) | L13: =IF(D13="","",D13-K13) | M13: =IF(OR(D13="",D13=0),"",L13/D13) | N13: =IF((E13+F13)=0,"",ROUND(L13/((E13+F13)/60),2))
I14: =IF(E14="","",ROUND(((E14+F14)/60)*'Cost Rates'!$B$3,2)) | J14: =IF(D14="","",'Cost Rates'!$B$4) | K14: =IF(D14="","",SUM(G14,H14,I14,J14)) | L14: =IF(D14="","",D14-K14) | M14: =IF(OR(D14="",D14=0),"",L14/D14) | N14: =IF((E14+F14)=0,"",ROUND(L14/((E14+F14)/60),2))
I15: =IF(E15="","",ROUND(((E15+F15)/60)*'Cost Rates'!$B$3,2)) | J15: =IF(D15="","",'Cost Rates'!$B$4) | K15: =IF(D15="","",SUM(G15,H15,I15,J15)) | L15: =IF(D15="","",D15-K15) | M15: =IF(OR(D15="",D15=0),"",L15/D15) | N15: =IF((E15+F15)=0,"",ROUND(L15/((E15+F15)/60),2))
... I400: =IF(E400="","",ROUND(((E400+F400)/60)*'Cost Rates'!$B$3,2)) | J400: =IF(D400="","",'Cost Rates'!$B$4) | K400: =IF(D400="","",SUM(G400,H400,I400,J400)) | L400: =IF(D400="","",D400-K400) | M400: =IF(OR(D400="",D400=0),"",L400/D400) | N400: =IF((E400+F400)=0,"",ROUND(L400/((E400+F400)/60),2))

Sheet Cost Rates
A1: COST RATES — set these once, revisit quarterly
A3: Labor cost per hour ($) | B3: 24 | C3: What the hour costs you. If you're solo, use what you'd pay someone to replace you — otherwise you'll think you're profitable when you've just worked for free.
A4: Equipment reserve per stop ($) | B4: 4 | C4: Mowers, trimmers, and blades wear out on a schedule. Charge yourself now so June's repair isn't a crisis.
A7: TOTALS
A8: Visits costed | B8: =COUNT('Visit Log'!D2:D400)
A9: Total revenue | B9: =SUM('Visit Log'!D2:D400)
A10: Total cost | B10: =SUM('Visit Log'!K2:K400)
A11: Total profit | B11: =SUM('Visit Log'!L2:L400)
A12: Average margin | B12: =IFERROR(AVERAGE('Visit Log'!M2:M400),"")
A13: Average true $/hr | B13: =IFERROR(AVERAGE('Visit Log'!N2:N400),"")
A15: Margins under 25% show red on the Visit Log. If the same client is red every week, that is not a bad week — that's a price that stopped working. Raise it or release the stop.
