Workbook

Sheet Start Here
A1: How to use this calculator 1. Go to the Rate Settings tab first. Set your target hourly rate, your minimum stop price, and check the mowing production rate against your own speed with your own mower. Those numbers drive everything. The defaults are sane starting points for a solo operator in a 2026 US suburban market — not gospel. 2. On the Calculator tab, fill in the yellow cells only: turf area, obstacle level, service type, frequency. The green cells do the math. 3. Quote the Per-Visit Price. Never quote hourly — customers shop hourly rates, they accept flat prices, and you're going to get faster at this every month. 4. If the Margin Check cell says FLOOR or LOW RATE, fix the price before you quote it. 5. Log every quote on the Quote Log tab to see your close rate and average stop value. The number new operators get wrong is TRIM TIME. A small lawn with a fence, a swing set, six trees, and a flower bed border takes longer than a big open lawn. That's what the obstacle factor is for — use it honestly and you'll stop losing money on 'small' yards. Convention: yellow cells = inputs (type here), green cells = outputs (never type here).

Sheet Calculator
A1: PROPERTY INPUTS
A3: Turf area to mow (sq ft) | B3: 8000 | C3: Turf only — subtract the house, drive, beds, and pool. A quarter-acre lot is rarely more than 8,000 sq ft of actual grass.
A4: Obstacle level | B4: Average | C4: Trees, beds, fences, play sets, and tight gates. This is the factor that makes small yards unprofitable when you ignore it.
A5: Service type | B5: Mow / Trim / Edge / Blow
A6: Frequency | B6: Weekly
A7: Gate access (walk-behind only)? | B7: No | C7: If the rider can't fit, production drops to the walk-behind rate
A8: Drive time from previous stop (min) | B8: 8 | C8: The whole business is route density — this is where it shows up
A9: Target hourly rate ($/hr) | B9: ='Rate Settings'!B3
A11: QUOTE OUTPUTS
A12: Mowing minutes | B12: =ROUND((B3/VLOOKUP(IF(B7="Yes","Walk-behind","Standard"),'Rate Settings'!A19:B20,2,FALSE))*60*VLOOKUP(B4,'Rate Settings'!A13:B15,2,FALSE),1)
A13: Total on-site minutes | B13: =ROUND(B12*VLOOKUP(B5,'Rate Settings'!A7:B10,2,FALSE)+'Rate Settings'!B4,1) | C13: Includes unload/load time from Rate Settings
A14: Per-visit price | B14: =MAX(CEILING((B13/60)*B9*VLOOKUP(B6,'Rate Settings'!A24:B27,2,FALSE),5),'Rate Settings'!B5)
A15: Effective $/hr (incl. drive) | B15: =IF((B13+B8)=0,"",ROUND(B14/((B13+B8)/60),2)) | C15: The honest number — drive time is unpaid time, and it's why density is everything
A16: Monthly (avg 4.33 visits) | B16: =IF(B6="Weekly",ROUND(B14*4.33,2),IF(B6="Biweekly",ROUND(B14*2.17,2),B14))
A17: Season estimate | B17: =IF(B6="Weekly",ROUND(B14*'Rate Settings'!B30,2),IF(B6="Biweekly",ROUND(B14*'Rate Settings'!B30/2,2),B14))
A18: Margin check | B18: =IF(B14<='Rate Settings'!B5,"FLOOR — priced at your minimum stop. Fine if it's on-route, skip it if it's a drive.",IF(B15<B9*0.9,"LOW RATE — effective hourly is more than 10% under target once drive time is counted. Raise the price or don't take the stop.","OK"))

Sheet Rate Settings
A1: RATE SETTINGS — all yellow, all yours
A3: Target hourly rate ($/hr revenue) | B3: 70 | C3: Solo operators: 55-90 is the workable band. This is revenue per on-site hour, not take-home.
A4: Unload / load time per stop (min) | B4: 5 | C4: Ramps down, ramps up, every single stop. Twenty stops a week is over an hour of unpaid time if you don't bill it.
A5: Minimum stop price ($) | B5: 45 | C5: The least you'll drop a ramp for. Below this, the stop costs you money no matter how small the yard is.
A6: SERVICE MULTIPLIERS (x mowing time)
A7: Mow / Trim / Edge / Blow | B7: 1.55 | C7: The full standard visit — trimming and edging are roughly half again the mow time
A8: Mow / Trim / Blow (no edging) | B8: 1.35
A9: Mow only | B9: 1
A10: Full service + bed maintenance | B10: 2.1
A12: OBSTACLE FACTORS
A13: Open | B13: 0.85 | C13: Wide open turf, few trees, no fence, straight passes
A14: Average | B14: 1
A15: Heavy | B15: 1.35 | C15: Fenced, many trees and beds, play equipment, tight corners. Price this honestly — it is the single most common reason a route is busy and broke.
A18: MOWING PRODUCTION (sq ft per hour)
A19: Standard | B19: 32000 | C19: A 48" stand-on or rider on open residential turf
A20: Walk-behind | B20: 20000 | C20: 36" walk-behind, or any yard where the gate forces the small mower
A23: FREQUENCY MULTIPLIERS
A24: Weekly | B24: 1 | C24: The baseline. Weekly clients are the route you're actually building.
A25: Biweekly | B25: 1.3 | C25: Costs MORE per visit, not less — double the growth, double the mess, same drive.
A26: Monthly | B26: 1.6
A27: One-Time | B27: 1.85 | C27: Overgrown one-offs are usually two cuts of work. Price them like it or decline them.
A29: SEASON
A30: Mowing weeks per season | B30: 30 | C30: Varies hugely by region — 26 in the north, 40+ in the south. Set yours.

Sheet Quote Log
A1: Date | B1: Customer | C1: Turf Sq Ft | D1: Obstacles | E1: Frequency | F1: Price/Visit ($) | G1: On-site Min | H1: Effective $/hr | I1: Won? | K1: Close rate | L1: =IFERROR(COUNTIF(I2:I500,"Won")/COUNTA(I2:I500),"")
A2: 46126 | B2: Okafor, D. | C2: 8000 | D2: Average | E2: Weekly | F2: 55 | G2: 34 | H2: =IF(G2=0,"",ROUND(F2/(G2/60),2)) | I2: Won | K2: Average stop | L2: =IFERROR(AVERAGE(F2:F500),"")
A3: 46128 | B3: Ruiz, M. | C3: 14000 | D3: Open | E3: Weekly | F3: 65 | G3: 41 | H3: =IF(G3=0,"",ROUND(F3/(G3/60),2)) | I3: Won | K3: Average $/hr | L3: =IFERROR(AVERAGE(H2:H500),"")
A4: 46131 | B4: Bell, S. | C4: 5000 | D4: Heavy | E4: Biweekly | F4: 60 | G4: 38 | H4: =IF(G4=0,"",ROUND(F4/(G4/60),2)) | I4: Lost
H5: =IF(G5=0,"",ROUND(F5/(G5/60),2))
H6: =IF(G6=0,"",ROUND(F6/(G6/60),2))
H7: =IF(G7=0,"",ROUND(F7/(G7/60),2))
H8: =IF(G8=0,"",ROUND(F8/(G8/60),2))
H9: =IF(G9=0,"",ROUND(F9/(G9/60),2))
H10: =IF(G10=0,"",ROUND(F10/(G10/60),2))
H11: =IF(G11=0,"",ROUND(F11/(G11/60),2))
H12: =IF(G12=0,"",ROUND(F12/(G12/60),2))
H13: =IF(G13=0,"",ROUND(F13/(G13/60),2))
H14: =IF(G14=0,"",ROUND(F14/(G14/60),2))
H15: =IF(G15=0,"",ROUND(F15/(G15/60),2))
H16: =IF(G16=0,"",ROUND(F16/(G16/60),2))
... H500: =IF(G500=0,"",ROUND(F500/(G500/60),2))
