Workbook

Sheet Start Here
A1: Recurring Client & Route Tracker — how to use The route IS the business. This workbook keeps every recurring client in one tab and shows you which route days earn and which ones are a truck payment disguised as a schedule. Clients tab: one row per recurring client. Set their service day, price, and on-site minutes. Route Days tab: totals each day automatically — stops, revenue, hours, and revenue per hour. A day under your target hourly rate is a day you're subsidizing with the good days. Density tab: the number that decides whether this business works. Drive time between stops is unpaid, and it is the difference between a $70/hr route and a $40/hr route with the same customers. Rule of thumb: if a prospect is more than 10 minutes off your existing route for that day, they need to pay a premium or wait until you have neighbors near them. Saying no to scattered work is how you build a tight route. Convention: yellow cells = inputs (type here), green cells = outputs (never type here).

Sheet Clients
A1: Client | B1: Address | C1: Phone | D1: Service Day | E1: Frequency | F1: Price/Visit ($) | G1: On-site Min | H1: Drive Min | I1: $/hr | J1: Billing | K1: Status | L1: Notes
A2: Okafor, D. | B2: 12 Larkspur Ln | C2: 555-0112 | D2: Monday | E2: Weekly | F2: 55 | G2: 34 | H2: 6 | I2: =IF(OR(G2="",(G2+H2)=0),"",ROUND(F2/((G2+H2)/60),2)) | J2: Monthly | K2: Active | L2: Invisible fence marked — see walkthrough form
A3: Ruiz, M. | B3: 28 Larkspur Ln | C3: 555-0128 | D3: Monday | E3: Weekly | F3: 65 | G3: 41 | H3: 2 | I3: =IF(OR(G3="",(G3+H3)=0),"",ROUND(F3/((G3+H3)/60),2)) | J3: Monthly | K3: Active | L3: Two doors down from Okafor — this is what density looks like
A4: Bell, S. | B4: 903 Highfield Rd | C4: 555-0193 | D4: Tuesday | E4: Biweekly | F4: 60 | G4: 38 | H4: 18 | I4: =IF(OR(G4="",(G4+H4)=0),"",ROUND(F4/((G4+H4)/60),2)) | J4: Per visit | K4: Active | L4: 18 min off route — first stop that day or it doesn't pay
I5: =IF(OR(G5="",(G5+H5)=0),"",ROUND(F5/((G5+H5)/60),2))
I6: =IF(OR(G6="",(G6+H6)=0),"",ROUND(F6/((G6+H6)/60),2))
I7: =IF(OR(G7="",(G7+H7)=0),"",ROUND(F7/((G7+H7)/60),2))
I8: =IF(OR(G8="",(G8+H8)=0),"",ROUND(F8/((G8+H8)/60),2))
I9: =IF(OR(G9="",(G9+H9)=0),"",ROUND(F9/((G9+H9)/60),2))
I10: =IF(OR(G10="",(G10+H10)=0),"",ROUND(F10/((G10+H10)/60),2))
I11: =IF(OR(G11="",(G11+H11)=0),"",ROUND(F11/((G11+H11)/60),2))
I12: =IF(OR(G12="",(G12+H12)=0),"",ROUND(F12/((G12+H12)/60),2))
I13: =IF(OR(G13="",(G13+H13)=0),"",ROUND(F13/((G13+H13)/60),2))
I14: =IF(OR(G14="",(G14+H14)=0),"",ROUND(F14/((G14+H14)/60),2))
I15: =IF(OR(G15="",(G15+H15)=0),"",ROUND(F15/((G15+H15)/60),2))
I16: =IF(OR(G16="",(G16+H16)=0),"",ROUND(F16/((G16+H16)/60),2))
... I300: =IF(OR(G300="",(G300+H300)=0),"",ROUND(F300/((G300+H300)/60),2))

Sheet Route Days
A1: ROUTE DAY BOARD
A2: Day | B2: Active Stops | C2: Revenue/Visit | D2: On-site Hrs | E2: Total Hrs (incl drive) | F2: $/hr
A3: Monday | B3: =COUNTIFS(Clients!D2:D300,A3,Clients!K2:K300,"Active") | C3: =SUMIFS(Clients!F2:F300,Clients!D2:D300,A3,Clients!K2:K300,"Active") | D3: =ROUND(SUMIFS(Clients!G2:G300,Clients!D2:D300,A3,Clients!K2:K300,"Active")/60,2) | E3: =ROUND((SUMIFS(Clients!G2:G300,Clients!D2:D300,A3,Clients!K2:K300,"Active")+SUMIFS(Clients!H2:H300,Clients!D2:D300,A3,Clients!K2:K300,"Active"))/60,2) | F3: =IF(E3=0,"",ROUND(C3/E3,2))
A4: Tuesday | B4: =COUNTIFS(Clients!D2:D300,A4,Clients!K2:K300,"Active") | C4: =SUMIFS(Clients!F2:F300,Clients!D2:D300,A4,Clients!K2:K300,"Active") | D4: =ROUND(SUMIFS(Clients!G2:G300,Clients!D2:D300,A4,Clients!K2:K300,"Active")/60,2) | E4: =ROUND((SUMIFS(Clients!G2:G300,Clients!D2:D300,A4,Clients!K2:K300,"Active")+SUMIFS(Clients!H2:H300,Clients!D2:D300,A4,Clients!K2:K300,"Active"))/60,2) | F4: =IF(E4=0,"",ROUND(C4/E4,2))
A5: Wednesday | B5: =COUNTIFS(Clients!D2:D300,A5,Clients!K2:K300,"Active") | C5: =SUMIFS(Clients!F2:F300,Clients!D2:D300,A5,Clients!K2:K300,"Active") | D5: =ROUND(SUMIFS(Clients!G2:G300,Clients!D2:D300,A5,Clients!K2:K300,"Active")/60,2) | E5: =ROUND((SUMIFS(Clients!G2:G300,Clients!D2:D300,A5,Clients!K2:K300,"Active")+SUMIFS(Clients!H2:H300,Clients!D2:D300,A5,Clients!K2:K300,"Active"))/60,2) | F5: =IF(E5=0,"",ROUND(C5/E5,2))
A6: Thursday | B6: =COUNTIFS(Clients!D2:D300,A6,Clients!K2:K300,"Active") | C6: =SUMIFS(Clients!F2:F300,Clients!D2:D300,A6,Clients!K2:K300,"Active") | D6: =ROUND(SUMIFS(Clients!G2:G300,Clients!D2:D300,A6,Clients!K2:K300,"Active")/60,2) | E6: =ROUND((SUMIFS(Clients!G2:G300,Clients!D2:D300,A6,Clients!K2:K300,"Active")+SUMIFS(Clients!H2:H300,Clients!D2:D300,A6,Clients!K2:K300,"Active"))/60,2) | F6: =IF(E6=0,"",ROUND(C6/E6,2))
A7: Friday | B7: =COUNTIFS(Clients!D2:D300,A7,Clients!K2:K300,"Active") | C7: =SUMIFS(Clients!F2:F300,Clients!D2:D300,A7,Clients!K2:K300,"Active") | D7: =ROUND(SUMIFS(Clients!G2:G300,Clients!D2:D300,A7,Clients!K2:K300,"Active")/60,2) | E7: =ROUND((SUMIFS(Clients!G2:G300,Clients!D2:D300,A7,Clients!K2:K300,"Active")+SUMIFS(Clients!H2:H300,Clients!D2:D300,A7,Clients!K2:K300,"Active"))/60,2) | F7: =IF(E7=0,"",ROUND(C7/E7,2))
A8: Saturday | B8: =COUNTIFS(Clients!D2:D300,A8,Clients!K2:K300,"Active") | C8: =SUMIFS(Clients!F2:F300,Clients!D2:D300,A8,Clients!K2:K300,"Active") | D8: =ROUND(SUMIFS(Clients!G2:G300,Clients!D2:D300,A8,Clients!K2:K300,"Active")/60,2) | E8: =ROUND((SUMIFS(Clients!G2:G300,Clients!D2:D300,A8,Clients!K2:K300,"Active")+SUMIFS(Clients!H2:H300,Clients!D2:D300,A8,Clients!K2:K300,"Active"))/60,2) | F8: =IF(E8=0,"",ROUND(C8/E8,2))
A10: TOTALS | B10: =SUM(B3:B8) | C10: =SUM(C3:C8) | D10: =SUM(D3:D8) | E10: =SUM(E3:E8) | F10: =IF(E10=0,"",ROUND(C10/E10,2))
A12: Weekly revenue (weekly clients) | B12: =SUMIFS(Clients!F2:F300,Clients!E2:E300,"Weekly",Clients!K2:K300,"Active")
A13: Monthly recurring estimate | B13: =ROUND(SUMIFS(Clients!F2:F300,Clients!E2:E300,"Weekly",Clients!K2:K300,"Active")*4.33+SUMIFS(Clients!F2:F300,Clients!E2:E300,"Biweekly",Clients!K2:K300,"Active")*2.17+SUMIFS(Clients!F2:F300,Clients!E2:E300,"Monthly",Clients!K2:K300,"Active"),2)
A15: Any day showing under $50/hr is being carried by your good days. Either raise those prices, tighten the stops, or move them to a day where they're on the way.

Sheet Density
A1: ROUTE DENSITY — the number that decides this business
A3: Active clients | B3: =COUNTIF(Clients!K2:K300,"Active")
A4: Total on-site hours per week | B4: =ROUND(SUMIF(Clients!K2:K300,"Active",Clients!G2:G300)/60,2)
A5: Total drive hours per week | B5: =ROUND(SUMIF(Clients!K2:K300,"Active",Clients!H2:H300)/60,2)
A6: Drive time as % of the day | B6: =IF((B4+B5)=0,"",B5/(B4+B5)) | C6: Under 15% is a tight route. Over 25% means you're being paid to drive, which nobody is.
A7: Average drive between stops (min) | B7: =IFERROR(ROUND(SUMIF(Clients!K2:K300,"Active",Clients!H2:H300)/B3,1),"")
A8: Average stop value | B8: =IFERROR(ROUND(SUMIF(Clients!K2:K300,"Active",Clients!F2:F300)/B3,2),"")
A9: Blended $/hr (incl. drive) | B9: =IF((B4+B5)=0,"",ROUND(SUMIF(Clients!K2:K300,"Active",Clients!F2:F300)/(B4+B5),2))
A11: WHAT TO DO WITH THIS
A12: If drive time is over 25%: stop taking scattered work. Fill in around the clients you already have — door hangers on the same street, a neighbor discount, and a polite 'not yet' to anyone across town. Density is worth more than the discount costs you.
A15: If blended $/hr is under your target: it is almost never the mowing that's slow. It's drive time, trim time on obstacle-heavy yards, and stops priced years ago that never got raised. Raise prices annually — every year you don't is a pay cut.
