Workbook

Sheet Start Here
A1: Income & Expense Tracker — how to use One row per transaction. Money in on the Income tab, money out on the Expenses tab, and the Summary tab totals it by month and by category. Do this weekly, not at tax time. Fifteen minutes on a Friday beats a lost weekend in April, and the expenses you forget are the deductions you donate to the IRS. The categories are set up for this trade — chemicals, equipment repair, fuel, and insurance are where your money actually goes. Change them to match your accountant's chart of accounts if you have one. This is a bookkeeping aid, not tax advice. Talk to a CPA about what's deductible in your situation. Convention: yellow cells = inputs (type here), green cells = outputs (never type here).

Sheet Income
A1: Date | B1: Customer | C1: Service | D1: Amount ($) | E1: Method | F1: Paid? | G1: Notes
A2: 46209 | B2: Alvarez, R. | C2: House Wash | D2: 350 | E2: Card | F2: Yes
A3: 46211 | B3: Nguyen, T. | C3: Driveway | D3: 225 | E3: Check | F3: Yes
A4: 46215 | B4: Whitaker, J. | C4: Deck | D4: 320 | E4: Invoice | F4: No

Sheet Expenses
A1: Date | B1: Vendor | C1: Category | D1: Amount ($) | E1: Notes
A2: 46204 | B2: Supply house | C2: Chemicals | D2: 145 | E2: SH, surfactant, gutter cleaner
A3: 46206 | B3: Fuel stop | C3: Fuel | D3: 78
A4: 46208 | B4: Insurance co. | C4: Insurance | D4: 165 | E4: Monthly GL premium

Sheet Summary
A1: SUMMARY
A3: Total income | B3: =SUM(Income!D2:D500)
A4: Collected | B4: =SUMIF(Income!F2:F500,"Yes",Income!D2:D500)
A5: Outstanding (unpaid) | B5: =SUMIF(Income!F2:F500,"No",Income!D2:D500) | C5: Chase anything here older than your terms — today, not next month
A6: Total expenses | B6: =SUM(Expenses!D2:D500)
A7: Net (income - expenses) | B7: =B3-B6
A8: Margin | B8: =IF(B3=0,"",B7/B3)
A10: Set aside for taxes | B10: =IF(B7<0,0,ROUND(B7*B11,2))
A11: Tax set-aside rate | B11: 0.25 | C11: Common rule of thumb for self-employment; confirm with your CPA
A13: EXPENSES BY CATEGORY
A14: Chemicals | B14: =SUMIF(Expenses!C2:C500,A14,Expenses!D2:D500) | C14: =IF($B$6=0,"",B14/$B$6)
A15: Fuel | B15: =SUMIF(Expenses!C2:C500,A15,Expenses!D2:D500) | C15: =IF($B$6=0,"",B15/$B$6)
A16: Equipment purchase | B16: =SUMIF(Expenses!C2:C500,A16,Expenses!D2:D500) | C16: =IF($B$6=0,"",B16/$B$6)
A17: Equipment repair/maintenance | B17: =SUMIF(Expenses!C2:C500,A17,Expenses!D2:D500) | C17: =IF($B$6=0,"",B17/$B$6)
A18: Insurance | B18: =SUMIF(Expenses!C2:C500,A18,Expenses!D2:D500) | C18: =IF($B$6=0,"",B18/$B$6)
A19: Vehicle/trailer | B19: =SUMIF(Expenses!C2:C500,A19,Expenses!D2:D500) | C19: =IF($B$6=0,"",B19/$B$6)
A20: Licenses & fees | B20: =SUMIF(Expenses!C2:C500,A20,Expenses!D2:D500) | C20: =IF($B$6=0,"",B20/$B$6)
A21: Marketing | B21: =SUMIF(Expenses!C2:C500,A21,Expenses!D2:D500) | C21: =IF($B$6=0,"",B21/$B$6)
A22: Software/apps | B22: =SUMIF(Expenses!C2:C500,A22,Expenses!D2:D500) | C22: =IF($B$6=0,"",B22/$B$6)
A23: Supplies | B23: =SUMIF(Expenses!C2:C500,A23,Expenses!D2:D500) | C23: =IF($B$6=0,"",B23/$B$6)
A24: Labor | B24: =SUMIF(Expenses!C2:C500,A24,Expenses!D2:D500) | C24: =IF($B$6=0,"",B24/$B$6)
A25: Other | B25: =SUMIF(Expenses!C2:C500,A25,Expenses!D2:D500) | C25: =IF($B$6=0,"",B25/$B$6)
